pywidevine/__init__.py
pywidevine/cdm.py
pywidevine/device.py
pywidevine/exceptions.py
pywidevine/key.py
pywidevine/license_protocol.proto
pywidevine/license_protocol_pb2.py
pywidevine/license_protocol_pb2.pyi
pywidevine/main.py
pywidevine/pssh.py
pywidevine/py.typed
pywidevine/remotecdm.py
pywidevine/serve.py
pywidevine/session.py
pywidevine/utils.py
pywidevinex-1.8.3.dist-info/entry_points.txt
pywidevinex-1.8.3.dist-info/licenses/LICENSE
pywidevinex-1.8.3.dist-info/METADATA
pywidevinex-1.8.3.dist-info/WHEEL
pywidevinex-1.8.3.dist-info/RECORD
